omnirec/__init__.py
omnirec/data_variants.py
omnirec/py.typed
omnirec/recsys_data_set.py
omnirec/cli/__init__.py
omnirec/cli/cmd_base.py
omnirec/cli/gen_algos.py
omnirec/cli/gen_datasets.py
omnirec/data_loaders/__init__.py
omnirec/data_loaders/adressa.py
omnirec/data_loaders/alibaba_i_fashion.py
omnirec/data_loaders/alibaba_mobile.py
omnirec/data_loaders/amazon2013.py
omnirec/data_loaders/amazon2014.py
omnirec/data_loaders/amazon2018.py
omnirec/data_loaders/amazon2023.py
omnirec/data_loaders/anime.py
omnirec/data_loaders/base.py
omnirec/data_loaders/beer.py
omnirec/data_loaders/behance.py
omnirec/data_loaders/bookcrossing.py
omnirec/data_loaders/ciaodvd.py
omnirec/data_loaders/citeulike.py
omnirec/data_loaders/datasets.py
omnirec/data_loaders/deliveryhero.py
omnirec/data_loaders/dianping_sequentialrec.py
omnirec/data_loaders/dianping_socialrec.py
omnirec/data_loaders/douban.py
omnirec/data_loaders/douban_short.py
omnirec/data_loaders/filmtrust.py
omnirec/data_loaders/frappe.py
omnirec/data_loaders/goodreads.py
omnirec/data_loaders/google_local2018.py
omnirec/data_loaders/google_local2021.py
omnirec/data_loaders/gowalla.py
omnirec/data_loaders/hetrec_lastfm.py
omnirec/data_loaders/jester.py
omnirec/data_loaders/konect.py
omnirec/data_loaders/movielens_100k.py
omnirec/data_loaders/movielens_1b_synthetic.py
omnirec/data_loaders/movielens_large.py
omnirec/data_loaders/movielens_small.py
omnirec/data_loaders/registry.py
omnirec/data_loaders/steam_australian_libraries.py
omnirec/data_loaders/steam_australian_reviews.py
omnirec/data_loaders/steam_recommendations.py
omnirec/data_loaders/steam_reviews.py
omnirec/data_loaders/yelp.py
omnirec/metrics/__init__.py
omnirec/metrics/base.py
omnirec/metrics/prediction.py
omnirec/metrics/ranking.py
omnirec/preprocess/__init__.py
omnirec/preprocess/base.py
omnirec/preprocess/core_pruning.py
omnirec/preprocess/feedback_conversion.py
omnirec/preprocess/filter.py
omnirec/preprocess/pipe.py
omnirec/preprocess/split.py
omnirec-0.2.0.dist-info/METADATA
omnirec-0.2.0.dist-info/WHEEL
omnirec-0.2.0.dist-info/entry_points.txt
omnirec-0.2.0.dist-info/RECORD
