Metadata-Version: 2.4
Name: omnirec
Version: 0.2.0
Summary: OmniRec: The all-in-one Python library providing a unified, cross-framework pipeline for reproducible and interoperable recommender system experimentation.
Project-URL: Homepage, https://omnirec.recommender-systems.com/
Project-URL: Documentation, https://omnirec.recommender-systems.com/getting_started/
Project-URL: Repository, https://github.com/ISG-Siegen/OmniRec
Author-email: "Intelligent Systems Group (ISG)" <pypi@isg.beel.org>
Requires-Python: >=3.12
Requires-Dist: cryptography>=45.0.6
Requires-Dist: dacite>=1.9.2
Requires-Dist: omnirec-runner
Requires-Dist: openpyxl>=3.1.5
Requires-Dist: pandas>=2.3.0
Requires-Dist: pydantic>=2.11.7
Requires-Dist: requests>=2.32.4
Requires-Dist: rich>=14.1.0
Requires-Dist: rpyc>=6.0.2
Requires-Dist: scikit-learn>=1.7.0
Requires-Dist: tqdm>=4.67.1
Requires-Dist: uv>=0.8.0
Requires-Dist: xlrd>=2.0.2
